{
  "step": 328,
  "timings": [
    {
      "name": "FluidSolver::adaptTimestep",
      "solver": "main",
      "ms": 0,
      "percent": 0.000000
    },
    {
      "name": "Shape::applyToGrid",
      "solver": "main",
      "ms": 0,
      "percent": 0.000000
    },
    {
      "name": "Timings::display",
      "ms": 0,
      "percent": 0.000000
    },
    {
      "name": "addBuoyancy",
      "solver": "main",
      "ms": 0,
      "percent": 0.000000
    },
    {
      "name": "calculateCurl",
      "solver": "main",
      "ms": 0,
      "percent": 0.000000
    },
    {
      "name": "computeVelocityMagnitude",
      "solver": "main",
      "ms": 1,
      "percent": 0.029806
    },
    {
      "name": "getMaxVal",
      "solver": "main",
      "ms": 0,
      "percent": 0.000000
    },
    {
      "name": "mantaMsg",
      "ms": 0,
      "percent": 0.000000
    },
    {
      "name": "massMomentumConservingAdvect",
      "solver": "main",
      "ms": 2189,
      "percent": 65.245902
    },
    {
      "name": "realGridStats",
      "solver": "main",
      "ms": 4,
      "percent": 0.119225
    },
    {
      "name": "setWallBcs",
      "solver": "main",
      "ms": 1,
      "percent": 0.029806
    },
    {
      "name": "solvePressure",
      "solver": "main",
      "ms": 1160,
      "percent": 34.575261
    }
  ],
  "total_ms": 3355
}
