{
  "step": 0,
  "timings": [
    {
      "name": "Box::Box",
      "solver": "main",
      "ms": 0,
      "percent": 0.000000
    },
    {
      "name": "Cylinder::Cylinder",
      "solver": "main",
      "ms": 0,
      "percent": 0.000000
    },
    {
      "name": "FlagGrid::FlagGrid",
      "solver": "main",
      "ms": 8,
      "percent": 0.023461
    },
    {
      "name": "FlagGrid::fillGrid",
      "solver": "main",
      "ms": 3,
      "percent": 0.008798
    },
    {
      "name": "FlagGrid::initDomain",
      "solver": "main",
      "ms": 9,
      "percent": 0.026394
    },
    {
      "name": "FluidSolver::FluidSolver",
      "solver": "main",
      "ms": 0,
      "percent": 0.000000
    },
    {
      "name": "FluidSolver::adaptTimestep",
      "solver": "main",
      "ms": 0,
      "percent": 0.000000
    },
    {
      "name": "Grid::Grid",
      "solver": "main",
      "ms": 41,
      "percent": 0.120238
    },
    {
      "name": "Grid::copyFrom",
      "solver": "main",
      "ms": 1,
      "percent": 0.002933
    },
    {
      "name": "LevelsetGrid::LevelsetGrid",
      "solver": "main",
      "ms": 17,
      "percent": 0.049855
    },
    {
      "name": "LevelsetGrid::subtract",
      "solver": "main",
      "ms": 2,
      "percent": 0.005865
    },
    {
      "name": "MACGrid::MACGrid",
      "solver": "main",
      "ms": 55,
      "percent": 0.161295
    },
    {
      "name": "Mesh::Mesh",
      "solver": "main",
      "ms": 0,
      "percent": 0.000000
    },
    {
      "name": "Mesh::computeLevelset",
      "solver": "main",
      "ms": 906,
      "percent": 2.656969
    },
    {
      "name": "Mesh::load",
      "solver": "main",
      "ms": 200,
      "percent": 0.586527
    },
    {
      "name": "Mesh::offset",
      "solver": "main",
      "ms": 0,
      "percent": 0.000000
    },
    {
      "name": "Mesh::scale",
      "solver": "main",
      "ms": 0,
      "percent": 0.000000
    },
    {
      "name": "Shape::applyToGrid",
      "solver": "main",
      "ms": 3,
      "percent": 0.008798
    },
    {
      "name": "Shape::computeLevelset",
      "solver": "main",
      "ms": 5,
      "percent": 0.014663
    },
    {
      "name": "Timings::Timings",
      "ms": 0,
      "percent": 0.000000
    },
    {
      "name": "addBuoyancy",
      "solver": "main",
      "ms": 4,
      "percent": 0.011731
    },
    {
      "name": "calculateCurl",
      "solver": "main",
      "ms": 6,
      "percent": 0.017596
    },
    {
      "name": "computeVelocityMagnitude",
      "solver": "main",
      "ms": 6,
      "percent": 0.017596
    },
    {
      "name": "fillWithOnes",
      "solver": "main",
      "ms": 7,
      "percent": 0.020528
    },
    {
      "name": "getMaxVal",
      "solver": "main",
      "ms": 0,
      "percent": 0.000000
    },
    {
      "name": "mantaMsg",
      "ms": 0,
      "percent": 0.000000
    },
    {
      "name": "realGridStats",
      "solver": "main",
      "ms": 29,
      "percent": 0.085046
    },
    {
      "name": "resetOutflow",
      "solver": "main",
      "ms": 4,
      "percent": 0.011731
    },
    {
      "name": "save",
      "ms": 177,
      "percent": 0.519077
    },
    {
      "name": "setObstacleFlags",
      "solver": "main",
      "ms": 2,
      "percent": 0.005865
    },
    {
      "name": "setOpenBound",
      "solver": "main",
      "ms": 13,
      "percent": 0.038124
    },
    {
      "name": "setWallBcs",
      "solver": "main",
      "ms": 5,
      "percent": 0.014663
    },
    {
      "name": "simpleSLAdvect",
      "solver": "main",
      "ms": 28208,
      "percent": 82.723834
    },
    {
      "name": "solvePressure",
      "solver": "main",
      "ms": 4388,
      "percent": 12.868413
    }
  ],
  "total_ms": 34099
}
