{
  "step": 632,
  "timings": [
    {
      "name": "FluidSolver::adaptTimestep",
      "solver": "main",
      "ms": 0,
      "percent": 0.000000
    },
    {
      "name": "Shape::applyToGrid",
      "solver": "main",
      "ms": 0,
      "percent": 0.000000
    },
    {
      "name": "Timings::display",
      "ms": 0,
      "percent": 0.000000
    },
    {
      "name": "addBuoyancy",
      "solver": "main",
      "ms": 1,
      "percent": 0.017803
    },
    {
      "name": "calculateCurl",
      "solver": "main",
      "ms": 1,
      "percent": 0.017803
    },
    {
      "name": "computeVelocityMagnitude",
      "solver": "main",
      "ms": 1,
      "percent": 0.017803
    },
    {
      "name": "getMaxVal",
      "solver": "main",
      "ms": 1,
      "percent": 0.017803
    },
    {
      "name": "mantaMsg",
      "ms": 0,
      "percent": 0.000000
    },
    {
      "name": "massMomentumConservingAdvect",
      "solver": "main",
      "ms": 4489,
      "percent": 79.918106
    },
    {
      "name": "realGridStats",
      "solver": "main",
      "ms": 5,
      "percent": 0.089015
    },
    {
      "name": "setWallBcs",
      "solver": "main",
      "ms": 0,
      "percent": 0.000000
    },
    {
      "name": "solvePressure",
      "solver": "main",
      "ms": 1119,
      "percent": 19.921666
    }
  ],
  "total_ms": 5617
}
