{
  "step": 72,
  "timings": [
    {
      "name": "FluidSolver::adaptTimestep",
      "solver": "main",
      "ms": 0,
      "percent": 0.000000
    },
    {
      "name": "Gui::nextRealGrid",
      "ms": 1,
      "percent": 0.014658
    },
    {
      "name": "Gui::screenshot",
      "ms": 0,
      "percent": 0.000000
    },
    {
      "name": "Gui::setCamPos",
      "ms": 0,
      "percent": 0.000000
    },
    {
      "name": "Gui::update",
      "ms": 426,
      "percent": 6.244503
    },
    {
      "name": "Gui::windowSize",
      "ms": 0,
      "percent": 0.000000
    },
    {
      "name": "Shape::applyToGrid",
      "solver": "main",
      "ms": 1,
      "percent": 0.014658
    },
    {
      "name": "Timings::display",
      "ms": 0,
      "percent": 0.000000
    },
    {
      "name": "addBuoyancy",
      "solver": "main",
      "ms": 0,
      "percent": 0.000000
    },
    {
      "name": "calculateCurl",
      "solver": "main",
      "ms": 0,
      "percent": 0.000000
    },
    {
      "name": "computeVelocityMagnitude",
      "solver": "main",
      "ms": 0,
      "percent": 0.000000
    },
    {
      "name": "getMaxVal",
      "solver": "main",
      "ms": 1,
      "percent": 0.014658
    },
    {
      "name": "mantaMsg",
      "ms": 1,
      "percent": 0.014658
    },
    {
      "name": "massMomentumConservingAdvect",
      "solver": "main",
      "ms": 4797,
      "percent": 70.316623
    },
    {
      "name": "realGridStats",
      "solver": "main",
      "ms": 4,
      "percent": 0.058634
    },
    {
      "name": "setWallBcs",
      "solver": "main",
      "ms": 1,
      "percent": 0.014658
    },
    {
      "name": "solvePressure",
      "solver": "main",
      "ms": 1590,
      "percent": 23.306948
    }
  ],
  "total_ms": 6822
}
