{
  "step": 43,
  "timings": [
    {
      "name": "FluidSolver::adaptTimestep",
      "solver": "main",
      "ms": 0,
      "percent": 0.000000
    },
    {
      "name": "Shape::applyToGrid",
      "solver": "main",
      "ms": 0,
      "percent": 0.000000
    },
    {
      "name": "Timings::display",
      "ms": 0,
      "percent": 0.000000
    },
    {
      "name": "addBuoyancy",
      "solver": "main",
      "ms": 0,
      "percent": 0.000000
    },
    {
      "name": "calculateCurl",
      "solver": "main",
      "ms": 0,
      "percent": 0.000000
    },
    {
      "name": "computeVelocityMagnitude",
      "solver": "main",
      "ms": 2,
      "percent": 0.214823
    },
    {
      "name": "getMaxVal",
      "solver": "main",
      "ms": 0,
      "percent": 0.000000
    },
    {
      "name": "mantaMsg",
      "ms": 0,
      "percent": 0.000000
    },
    {
      "name": "massMomentumConservingAdvect",
      "solver": "main",
      "ms": 741,
      "percent": 79.591837
    },
    {
      "name": "realGridStats",
      "solver": "main",
      "ms": 1,
      "percent": 0.107411
    },
    {
      "name": "setWallBcs",
      "solver": "main",
      "ms": 0,
      "percent": 0.000000
    },
    {
      "name": "solvePressure",
      "solver": "main",
      "ms": 187,
      "percent": 20.085929
    }
  ],
  "total_ms": 931
}
