{
  "step": 550,
  "timings": [
    {
      "name": "FluidSolver::adaptTimestep",
      "solver": "main",
      "ms": 0,
      "percent": 0.000000
    },
    {
      "name": "Shape::applyToGrid",
      "solver": "main",
      "ms": 0,
      "percent": 0.000000
    },
    {
      "name": "Timings::display",
      "ms": 1,
      "percent": 0.091743
    },
    {
      "name": "addBuoyancy",
      "solver": "main",
      "ms": 0,
      "percent": 0.000000
    },
    {
      "name": "calculateCurl",
      "solver": "main",
      "ms": 0,
      "percent": 0.000000
    },
    {
      "name": "computeVelocityMagnitude",
      "solver": "main",
      "ms": 1,
      "percent": 0.091743
    },
    {
      "name": "getMaxVal",
      "solver": "main",
      "ms": 0,
      "percent": 0.000000
    },
    {
      "name": "mantaMsg",
      "ms": 0,
      "percent": 0.000000
    },
    {
      "name": "massMomentumConservingAdvect",
      "solver": "main",
      "ms": 896,
      "percent": 82.201835
    },
    {
      "name": "realGridStats",
      "solver": "main",
      "ms": 2,
      "percent": 0.183486
    },
    {
      "name": "setWallBcs",
      "solver": "main",
      "ms": 0,
      "percent": 0.000000
    },
    {
      "name": "solvePressure",
      "solver": "main",
      "ms": 190,
      "percent": 17.431193
    }
  ],
  "total_ms": 1090
}
