{
  "step": 6,
  "timings": [
    {
      "name": "FluidSolver::adaptTimestep",
      "solver": "main",
      "ms": 0,
      "percent": 0.000000
    },
    {
      "name": "Shape::applyToGrid",
      "solver": "main",
      "ms": 3,
      "percent": 0.003225
    },
    {
      "name": "Timings::display",
      "ms": 0,
      "percent": 0.000000
    },
    {
      "name": "addBuoyancy",
      "solver": "main",
      "ms": 9,
      "percent": 0.009676
    },
    {
      "name": "calculateCurl",
      "solver": "main",
      "ms": 12,
      "percent": 0.012902
    },
    {
      "name": "computeVelocityMagnitude",
      "solver": "main",
      "ms": 15,
      "percent": 0.016127
    },
    {
      "name": "getMaxVal",
      "solver": "main",
      "ms": 2,
      "percent": 0.002150
    },
    {
      "name": "mantaMsg",
      "ms": 0,
      "percent": 0.000000
    },
    {
      "name": "realGridStats",
      "solver": "main",
      "ms": 50,
      "percent": 0.053757
    },
    {
      "name": "resetOutflow",
      "solver": "main",
      "ms": 11,
      "percent": 0.011826
    },
    {
      "name": "save",
      "ms": 231,
      "percent": 0.248355
    },
    {
      "name": "setWallBcs",
      "solver": "main",
      "ms": 5,
      "percent": 0.005376
    },
    {
      "name": "simpleSLAdvect",
      "solver": "main",
      "ms": 80921,
      "percent": 87.000602
    },
    {
      "name": "solvePressure",
      "solver": "main",
      "ms": 11753,
      "percent": 12.636004
    }
  ],
  "total_ms": 93012
}
