{
  "step": 13,
  "timings": [
    {
      "name": "FluidSolver::adaptTimestep",
      "solver": "main",
      "ms": 0,
      "percent": 0.000000
    },
    {
      "name": "Shape::applyToGrid",
      "solver": "main",
      "ms": 4,
      "percent": 0.004668
    },
    {
      "name": "Timings::display",
      "ms": 0,
      "percent": 0.000000
    },
    {
      "name": "addBuoyancy",
      "solver": "main",
      "ms": 9,
      "percent": 0.010502
    },
    {
      "name": "calculateCurl",
      "solver": "main",
      "ms": 12,
      "percent": 0.014003
    },
    {
      "name": "computeVelocityMagnitude",
      "solver": "main",
      "ms": 13,
      "percent": 0.015170
    },
    {
      "name": "getMaxVal",
      "solver": "main",
      "ms": 3,
      "percent": 0.003501
    },
    {
      "name": "mantaMsg",
      "ms": 0,
      "percent": 0.000000
    },
    {
      "name": "realGridStats",
      "solver": "main",
      "ms": 48,
      "percent": 0.056013
    },
    {
      "name": "resetOutflow",
      "solver": "main",
      "ms": 11,
      "percent": 0.012836
    },
    {
      "name": "setWallBcs",
      "solver": "main",
      "ms": 5,
      "percent": 0.005835
    },
    {
      "name": "simpleSLAdvect",
      "solver": "main",
      "ms": 73800,
      "percent": 86.119377
    },
    {
      "name": "solvePressure",
      "solver": "main",
      "ms": 11790,
      "percent": 13.758096
    }
  ],
  "total_ms": 85695
}
