{
  "step": 37,
  "timings": [
    {
      "name": "FluidSolver::adaptTimestep",
      "solver": "main",
      "ms": 0,
      "percent": 0.000000
    },
    {
      "name": "Shape::applyToGrid",
      "solver": "main",
      "ms": 2,
      "percent": 0.000662
    },
    {
      "name": "Timings::display",
      "ms": 0,
      "percent": 0.000000
    },
    {
      "name": "addBuoyancy",
      "solver": "main",
      "ms": 4,
      "percent": 0.001324
    },
    {
      "name": "calculateCurl",
      "solver": "main",
      "ms": 5,
      "percent": 0.001655
    },
    {
      "name": "computeVelocityMagnitude",
      "solver": "main",
      "ms": 6,
      "percent": 0.001986
    },
    {
      "name": "getMaxVal",
      "solver": "main",
      "ms": 2,
      "percent": 0.000662
    },
    {
      "name": "mantaMsg",
      "ms": 0,
      "percent": 0.000000
    },
    {
      "name": "massMomentumConservingAdvect",
      "solver": "main",
      "ms": 297922,
      "percent": 98.604937
    },
    {
      "name": "realGridStats",
      "solver": "main",
      "ms": 44,
      "percent": 0.014563
    },
    {
      "name": "resetOutflow",
      "solver": "main",
      "ms": 7,
      "percent": 0.002317
    },
    {
      "name": "save",
      "ms": 55,
      "percent": 0.018204
    },
    {
      "name": "setWallBcs",
      "solver": "main",
      "ms": 4,
      "percent": 0.001324
    },
    {
      "name": "solvePressure",
      "solver": "main",
      "ms": 4086,
      "percent": 1.352367
    }
  ],
  "total_ms": 302137
}
