{
  "step": 28,
  "timings": [
    {
      "name": "FluidSolver::adaptTimestep",
      "solver": "main",
      "ms": 0,
      "percent": 0.000000
    },
    {
      "name": "Shape::applyToGrid",
      "solver": "main",
      "ms": 4,
      "percent": 0.000525
    },
    {
      "name": "Timings::display",
      "ms": 0,
      "percent": 0.000000
    },
    {
      "name": "addBuoyancy",
      "solver": "main",
      "ms": 9,
      "percent": 0.001182
    },
    {
      "name": "calculateCurl",
      "solver": "main",
      "ms": 14,
      "percent": 0.001838
    },
    {
      "name": "computeVelocityMagnitude",
      "solver": "main",
      "ms": 15,
      "percent": 0.001970
    },
    {
      "name": "getMaxVal",
      "solver": "main",
      "ms": 2,
      "percent": 0.000263
    },
    {
      "name": "mantaMsg",
      "ms": 0,
      "percent": 0.000000
    },
    {
      "name": "massMomentumConservingAdvect",
      "solver": "main",
      "ms": 749177,
      "percent": 98.375804
    },
    {
      "name": "realGridStats",
      "solver": "main",
      "ms": 50,
      "percent": 0.006566
    },
    {
      "name": "resetOutflow",
      "solver": "main",
      "ms": 12,
      "percent": 0.001576
    },
    {
      "name": "save",
      "ms": 228,
      "percent": 0.029939
    },
    {
      "name": "setWallBcs",
      "solver": "main",
      "ms": 5,
      "percent": 0.000657
    },
    {
      "name": "solvePressure",
      "solver": "main",
      "ms": 12030,
      "percent": 1.579681
    }
  ],
  "total_ms": 761546
}
